magic_wormhole-0.21.0.data/data/wormhole_complete.bash
magic_wormhole-0.21.0.data/data/wormhole_complete.fish
magic_wormhole-0.21.0.data/data/wormhole_complete.zsh
magic_wormhole-0.21.0.dist-info/licenses/LICENSE
wormhole/__init__.py
wormhole/__main__.py
wormhole/_allocator.py
wormhole/_boss.py
wormhole/_code.py
wormhole/_hints.py
wormhole/_input.py
wormhole/_interfaces.py
wormhole/_key.py
wormhole/_lister.py
wormhole/_mailbox.py
wormhole/_nameplate.py
wormhole/_order.py
wormhole/_receive.py
wormhole/_rendezvous.py
wormhole/_rlcompleter.py
wormhole/_send.py
wormhole/_status.py
wormhole/_terminator.py
wormhole/_version.py
wormhole/_wordlist.py
wormhole/errors.py
wormhole/eventual.py
wormhole/ipaddrs.py
wormhole/journal.py
wormhole/observer.py
wormhole/timing.py
wormhole/tor_manager.py
wormhole/transit.py
wormhole/util.py
wormhole/wormhole.py
wormhole/xfer_util.py
wormhole/_dilation/__init__.py
wormhole/_dilation/_noise.py
wormhole/_dilation/connection.py
wormhole/_dilation/connector.py
wormhole/_dilation/encode.py
wormhole/_dilation/inbound.py
wormhole/_dilation/manager.py
wormhole/_dilation/outbound.py
wormhole/_dilation/roles.py
wormhole/_dilation/subchannel.py
wormhole/cli/__init__.py
wormhole/cli/cli.py
wormhole/cli/cmd_receive.py
wormhole/cli/cmd_send.py
wormhole/cli/cmd_ssh.py
wormhole/cli/public_relay.py
wormhole/cli/welcome.py
wormhole/test/__init__.py
wormhole/test/common.py
wormhole/test/conftest.py
wormhole/test/test_args.py
wormhole/test/test_cli.py
wormhole/test/test_eventual.py
wormhole/test/test_hints.py
wormhole/test/test_hkdf.py
wormhole/test/test_ipaddrs.py
wormhole/test/test_journal.py
wormhole/test/test_keys.py
wormhole/test/test_machines.py
wormhole/test/test_observer.py
wormhole/test/test_rlcompleter.py
wormhole/test/test_ssh.py
wormhole/test/test_tor_manager.py
wormhole/test/test_transit.py
wormhole/test/test_util.py
wormhole/test/test_util_attrs_zope.py
wormhole/test/test_wordlist.py
wormhole/test/test_wormhole.py
wormhole/test/test_xfer_util.py
wormhole/test/dilate/__init__.py
magic_wormhole-0.21.0.dist-info/METADATA
magic_wormhole-0.21.0.dist-info/WHEEL
magic_wormhole-0.21.0.dist-info/entry_points.txt
magic_wormhole-0.21.0.dist-info/top_level.txt
magic_wormhole-0.21.0.dist-info/RECORD
