Metadata-Version: 2.4
Name: magic-wormhole
Version: 0.21.0
Summary: Securely transfer data between computers
Home-page: https://github.com/warner/magic-wormhole
Author: Brian Warner
Author-email: warner-magic-wormhole@lothar.com
License: MIT
Classifier: Development Status :: 4 - Beta
Classifier: Environment :: Console
Classifier: Programming Language :: Python :: 3
Classifier: Programming Language :: Python :: 3.10
Classifier: Programming Language :: Python :: 3.11
Classifier: Programming Language :: Python :: 3.12
Classifier: Programming Language :: Python :: Implementation :: CPython
Classifier: Topic :: Security :: Cryptography
Classifier: Topic :: System :: Networking
Classifier: Topic :: System :: Systems Administration
Classifier: Topic :: Utilities
Requires-Python: >=3.10
License-File: LICENSE
Requires-Dist: spake2==0.9
Requires-Dist: pynacl
Requires-Dist: attrs>=19.2.0
Requires-Dist: twisted[tls]>=17.5.0
Requires-Dist: autobahn[twisted]!=25.10.1,!=25.9.1,>=0.14.1
Requires-Dist: automat
Requires-Dist: cryptography
Requires-Dist: tqdm>=4.13.0
Requires-Dist: click
Requires-Dist: humanize
Requires-Dist: txtorcon>=18.0.2
Requires-Dist: zipstream-ng<2.0.0,>=1.7.1
Requires-Dist: iterable-io<2.0.0,>=1.0.0
Requires-Dist: qrcode>=8.0
Requires-Dist: pywin32; sys_platform == "win32"
Provides-Extra: dev
Requires-Dist: tox; extra == "dev"
Requires-Dist: pyflakes; extra == "dev"
Requires-Dist: magic-wormhole-transit-relay; extra == "dev"
Requires-Dist: magic-wormhole-mailbox-server; extra == "dev"
Requires-Dist: pytest; extra == "dev"
Requires-Dist: pytest_twisted; extra == "dev"
Requires-Dist: hypothesis; extra == "dev"
Provides-Extra: dilate
Requires-Dist: noiseprotocol; extra == "dilate"
Provides-Extra: build
Requires-Dist: twine; extra == "build"
Requires-Dist: dulwich; extra == "build"
Requires-Dist: readme_renderer; extra == "build"
Requires-Dist: pysequoia; extra == "build"
Requires-Dist: wheel; extra == "build"
Dynamic: author
Dynamic: author-email
Dynamic: classifier
Dynamic: description
Dynamic: description-content-type
Dynamic: home-page
Dynamic: license
Dynamic: license-file
Dynamic: provides-extra
Dynamic: requires-dist
Dynamic: requires-python
Dynamic: summary
